[
  {
    "id": "NTF-00001",
    "title": "Compliance document pending",
    "description": "Mismatch detected in GRN",
    "channel": "Email",
    "recipient": "user18@example.com",
    "priority": "Critical",
    "status": "Read",
    "module": "Invoice",
    "entityId": "ENT-14357",
    "createdAt": "2026-05-07T12:00:00Z",
    "updatedAt": "2026-05-11T12:00:00Z",
    "scheduledAt": "2026-05-15T12:00:00Z",
    "deliveredAt": "2026-05-11T12:00:00Z",
    "deliveryAttempts": 3,
    "template": "compliance-reminder",
    "actionUrl": "/dashboard",
    "metadata": {
      "source": "System"
    }
  },
  {
    "id": "NTF-00002",
    "title": "Payment success",
    "description": "Retry queued for bank gateway",
    "channel": "Email",
    "recipient": "user2@example.com",
    "priority": "Medium",
    "status": "Read",
    "module": "Invoice",
    "entityId": "ENT-49794",
    "createdAt": "2026-05-13T12:00:00Z",
    "updatedAt": "2026-05-13T12:00:00Z",
    "scheduledAt": "2026-05-09T12:00:00Z",
    "deliveredAt": "2026-05-11T12:00:00Z",
    "deliveryAttempts": 3,
    "template": "approval-request",
    "actionUrl": "/dashboard",
    "metadata": {
      "source": "System"
    }
  },
  {
    "id": "NTF-00003",
    "title": "Payment success",
    "description": "KYC document missing",
    "channel": "Email",
    "recipient": "user17@example.com",
    "priority": "High",
    "status": "Read",
    "module": "Audit",
    "entityId": "ENT-16257",
    "createdAt": "2026-05-08T12:00:00Z",
    "updatedAt": "2026-05-11T12:00:00Z",
    "scheduledAt": "2026-05-14T12:00:00Z",
    "deliveredAt": "2026-05-11T12:00:00Z",
    "deliveryAttempts": 2,
    "template": "workflow-alert",
    "actionUrl": "/dashboard",
    "metadata": {
      "source": "API"
    }
  },
  {
    "id": "NTF-00004",
    "title": "Compliance document pending",
    "description": "Mismatch detected in GRN",
    "channel": "SMS",
    "recipient": "user25@example.com",
    "priority": "Medium",
    "status": "Sent",
    "module": "Invoice",
    "entityId": "ENT-77344",
    "createdAt": "2026-05-13T12:00:00Z",
    "updatedAt": "2026-05-11T12:00:00Z",
    "scheduledAt": "2026-05-14T12:00:00Z",
    "deliveredAt": "",
    "deliveryAttempts": 3,
    "template": "compliance-reminder",
    "actionUrl": "/dashboard",
    "metadata": {
      "source": "User"
    }
  },
  {
    "id": "NTF-00005",
    "title": "Invoice needs attention",
    "description": "Action required on invoice",
    "channel": "In-app",
    "recipient": "user22@example.com",
    "priority": "Critical",
    "status": "Read",
    "module": "Audit",
    "entityId": "ENT-45721",
    "createdAt": "2026-05-12T12:00:00Z",
    "updatedAt": "2026-05-13T12:00:00Z",
    "scheduledAt": "2026-05-13T12:00:00Z",
    "deliveredAt": "",
    "deliveryAttempts": 3,
    "template": "workflow-alert",
    "actionUrl": "/dashboard",
    "metadata": {
      "source": "API"
    }
  },
  {
    "id": "NTF-00006",
    "title": "Compliance document pending",
    "description": "Retry queued for bank gateway",
    "channel": "In-app",
    "recipient": "user20@example.com",
    "priority": "Medium",
    "status": "Failed",
    "module": "Audit",
    "entityId": "ENT-35205",
    "createdAt": "2026-05-11T12:00:00Z",
    "updatedAt": "2026-05-11T12:00:00Z",
    "scheduledAt": "2026-05-11T12:00:00Z",
    "deliveredAt": "2026-05-11T12:00:00Z",
    "deliveryAttempts": 3,
    "template": "payment-summary",
    "actionUrl": "/dashboard",
    "metadata": {
      "source": "API"
    }
  },
  {
    "id": "NTF-00007",
    "title": "Vendor onboarding approved",
    "description": "Payment settled successfully",
    "channel": "SMS",
    "recipient": "user9@example.com",
    "priority": "Medium",
    "status": "Failed",
    "module": "Vendor",
    "entityId": "ENT-10321",
    "createdAt": "2026-05-11T12:00:00Z",
    "updatedAt": "2026-05-13T12:00:00Z",
    "scheduledAt": "2026-05-12T12:00:00Z",
    "deliveredAt": "2026-05-12T12:00:00Z",
    "deliveryAttempts": 1,
    "template": "workflow-alert",
    "actionUrl": "/dashboard",
    "metadata": {
      "source": "System"
    }
  },
  {
    "id": "NTF-00008",
    "title": "Payment failed",
    "description": "KYC document missing",
    "channel": "In-app",
    "recipient": "user20@example.com",
    "priority": "High",
    "status": "Unread",
    "module": "Invoice",
    "entityId": "ENT-51737",
    "createdAt": "2026-05-06T12:00:00Z",
    "updatedAt": "2026-05-13T12:00:00Z",
    "scheduledAt": "2026-05-13T12:00:00Z",
    "deliveredAt": "2026-05-12T12:00:00Z",
    "deliveryAttempts": 3,
    "template": "compliance-reminder",
    "actionUrl": "/dashboard",
    "metadata": {
      "source": "API"
    }
  },
  {
    "id": "NTF-00009",
    "title": "3-way match failed",
    "description": "Retry queued for bank gateway",
    "channel": "Slack",
    "recipient": "user19@example.com",
    "priority": "Medium",
    "status": "Read",
    "module": "Matching",
    "entityId": "ENT-59142",
    "createdAt": "2026-05-07T12:00:00Z",
    "updatedAt": "2026-05-11T12:00:00Z",
    "scheduledAt": "2026-05-14T12:00:00Z",
    "deliveredAt": "2026-05-11T12:00:00Z",
    "deliveryAttempts": 2,
    "template": "payment-summary",
    "actionUrl": "/dashboard",
    "metadata": {
      "source": "System"
    }
  },
  {
    "id": "NTF-00010",
    "title": "Payment success",
    "description": "Retry queued for bank gateway",
    "channel": "In-app",
    "recipient": "user9@example.com",
    "priority": "Low",
    "status": "Sent",
    "module": "Vendor",
    "entityId": "ENT-66026",
    "createdAt": "2026-05-08T12:00:00Z",
    "updatedAt": "2026-05-13T12:00:00Z",
    "scheduledAt": "2026-05-15T12:00:00Z",
    "deliveredAt": "",
    "deliveryAttempts": 1,
    "template": "compliance-reminder",
    "actionUrl": "/dashboard",
    "metadata": {
      "source": "User"
    }
  },
  {
    "id": "NTF-00011",
    "title": "Payment failed",
    "description": "Mismatch detected in GRN",
    "channel": "Email",
    "recipient": "user16@example.com",
    "priority": "Critical",
    "status": "Sent",
    "module": "Matching",
    "entityId": "ENT-28613",
    "createdAt": "2026-05-11T12:00:00Z",
    "updatedAt": "2026-05-11T12:00:00Z",
    "scheduledAt": "2026-05-15T12:00:00Z",
    "deliveredAt": "2026-05-13T12:00:00Z",
    "deliveryAttempts": 1,
    "template": "workflow-alert",
    "actionUrl": "/dashboard",
    "metadata": {
      "source": "System"
    }
  },
  {
    "id": "NTF-00012",
    "title": "Compliance document pending",
    "description": "Payment settled successfully",
    "channel": "Slack",
    "recipient": "user24@example.com",
    "priority": "Medium",
    "status": "Failed",
    "module": "Audit",
    "entityId": "ENT-53337",
    "createdAt": "2026-05-06T12:00:00Z",
    "updatedAt": "2026-05-13T12:00:00Z",
    "scheduledAt": "2026-05-14T12:00:00Z",
    "deliveredAt": "",
    "deliveryAttempts": 2,
    "template": "workflow-alert",
    "actionUrl": "/dashboard",
    "metadata": {
      "source": "System"
    }
  },
  {
    "id": "NTF-00013",
    "title": "Compliance document pending",
    "description": "Payment settled successfully",
    "channel": "Email",
    "recipient": "user9@example.com",
    "priority": "Medium",
    "status": "Failed",
    "module": "Approval",
    "entityId": "ENT-15560",
    "createdAt": "2026-05-07T12:00:00Z",
    "updatedAt": "2026-05-12T12:00:00Z",
    "scheduledAt": "2026-05-13T12:00:00Z",
    "deliveredAt": "2026-05-11T12:00:00Z",
    "deliveryAttempts": 1,
    "template": "workflow-alert",
    "actionUrl": "/dashboard",
    "metadata": {
      "source": "API"
    }
  },
  {
    "id": "NTF-00014",
    "title": "Approval escalated",
    "description": "Payment settled successfully",
    "channel": "Email",
    "recipient": "user13@example.com",
    "priority": "Medium",
    "status": "Unread",
    "module": "Payment",
    "entityId": "ENT-17104",
    "createdAt": "2026-05-10T12:00:00Z",
    "updatedAt": "2026-05-11T12:00:00Z",
    "scheduledAt": "2026-05-15T12:00:00Z",
    "deliveredAt": "2026-05-13T12:00:00Z",
    "deliveryAttempts": 2,
    "template": "compliance-reminder",
    "actionUrl": "/dashboard",
    "metadata": {
      "source": "System"
    }
  },
  {
    "id": "NTF-00015",
    "title": "Payment success",
    "description": "KYC document missing",
    "channel": "Slack",
    "recipient": "user7@example.com",
    "priority": "Low",
    "status": "Read",
    "module": "Payment",
    "entityId": "ENT-70891",
    "createdAt": "2026-05-12T12:00:00Z",
    "updatedAt": "2026-05-11T12:00:00Z",
    "scheduledAt": "2026-05-10T12:00:00Z",
    "deliveredAt": "2026-05-13T12:00:00Z",
    "deliveryAttempts": 1,
    "template": "workflow-alert",
    "actionUrl": "/dashboard",
    "metadata": {
      "source": "System"
    }
  },
  {
    "id": "NTF-00016",
    "title": "Vendor onboarding approved",
    "description": "Mismatch detected in GRN",
    "channel": "In-app",
    "recipient": "user10@example.com",
    "priority": "Low",
    "status": "Failed",
    "module": "Audit",
    "entityId": "ENT-64496",
    "createdAt": "2026-05-07T12:00:00Z",
    "updatedAt": "2026-05-12T12:00:00Z",
    "scheduledAt": "2026-05-11T12:00:00Z",
    "deliveredAt": "2026-05-11T12:00:00Z",
    "deliveryAttempts": 1,
    "template": "approval-request",
    "actionUrl": "/dashboard",
    "metadata": {
      "source": "System"
    }
  },
  {
    "id": "NTF-00017",
    "title": "Payment failed",
    "description": "Mismatch detected in GRN",
    "channel": "SMS",
    "recipient": "user8@example.com",
    "priority": "Medium",
    "status": "Unread",
    "module": "Audit",
    "entityId": "ENT-95489",
    "createdAt": "2026-05-06T12:00:00Z",
    "updatedAt": "2026-05-13T12:00:00Z",
    "scheduledAt": "2026-05-12T12:00:00Z",
    "deliveredAt": "2026-05-13T12:00:00Z",
    "deliveryAttempts": 1,
    "template": "approval-request",
    "actionUrl": "/dashboard",
    "metadata": {
      "source": "User"
    }
  },
  {
    "id": "NTF-00018",
    "title": "Invoice needs attention",
    "description": "Payment settled successfully",
    "channel": "Slack",
    "recipient": "user18@example.com",
    "priority": "Critical",
    "status": "Read",
    "module": "Audit",
    "entityId": "ENT-72801",
    "createdAt": "2026-05-08T12:00:00Z",
    "updatedAt": "2026-05-12T12:00:00Z",
    "scheduledAt": "2026-05-13T12:00:00Z",
    "deliveredAt": "2026-05-11T12:00:00Z",
    "deliveryAttempts": 2,
    "template": "workflow-alert",
    "actionUrl": "/dashboard",
    "metadata": {
      "source": "System"
    }
  },
  {
    "id": "NTF-00019",
    "title": "3-way match failed",
    "description": "Mismatch detected in GRN",
    "channel": "Slack",
    "recipient": "user19@example.com",
    "priority": "Low",
    "status": "Read",
    "module": "Vendor",
    "entityId": "ENT-46614",
    "createdAt": "2026-05-09T12:00:00Z",
    "updatedAt": "2026-05-11T12:00:00Z",
    "scheduledAt": "2026-05-12T12:00:00Z",
    "deliveredAt": "",
    "deliveryAttempts": 3,
    "template": "approval-request",
    "actionUrl": "/dashboard",
    "metadata": {
      "source": "User"
    }
  },
  {
    "id": "NTF-00020",
    "title": "Compliance document pending",
    "description": "Action required on invoice",
    "channel": "Email",
    "recipient": "user23@example.com",
    "priority": "High",
    "status": "Unread",
    "module": "Approval",
    "entityId": "ENT-92739",
    "createdAt": "2026-05-10T12:00:00Z",
    "updatedAt": "2026-05-13T12:00:00Z",
    "scheduledAt": "2026-05-10T12:00:00Z",
    "deliveredAt": "",
    "deliveryAttempts": 1,
    "template": "compliance-reminder",
    "actionUrl": "/dashboard",
    "metadata": {
      "source": "System"
    }
  },
  {
    "id": "NTF-00021",
    "title": "Payment failed",
    "description": "Retry queued for bank gateway",
    "channel": "In-app",
    "recipient": "user13@example.com",
    "priority": "Low",
    "status": "Failed",
    "module": "Approval",
    "entityId": "ENT-36249",
    "createdAt": "2026-05-09T12:00:00Z",
    "updatedAt": "2026-05-12T12:00:00Z",
    "scheduledAt": "2026-05-10T12:00:00Z",
    "deliveredAt": "",
    "deliveryAttempts": 3,
    "template": "workflow-alert",
    "actionUrl": "/dashboard",
    "metadata": {
      "source": "API"
    }
  },
  {
    "id": "NTF-00022",
    "title": "Invoice needs attention",
    "description": "Action required on invoice",
    "channel": "Slack",
    "recipient": "user13@example.com",
    "priority": "High",
    "status": "Read",
    "module": "Approval",
    "entityId": "ENT-89880",
    "createdAt": "2026-05-12T12:00:00Z",
    "updatedAt": "2026-05-11T12:00:00Z",
    "scheduledAt": "2026-05-13T12:00:00Z",
    "deliveredAt": "2026-05-13T12:00:00Z",
    "deliveryAttempts": 1,
    "template": "payment-summary",
    "actionUrl": "/dashboard",
    "metadata": {
      "source": "User"
    }
  },
  {
    "id": "NTF-00023",
    "title": "Vendor onboarding approved",
    "description": "Retry queued for bank gateway",
    "channel": "Slack",
    "recipient": "user5@example.com",
    "priority": "High",
    "status": "Unread",
    "module": "Audit",
    "entityId": "ENT-42467",
    "createdAt": "2026-05-13T12:00:00Z",
    "updatedAt": "2026-05-12T12:00:00Z",
    "scheduledAt": "2026-05-09T12:00:00Z",
    "deliveredAt": "",
    "deliveryAttempts": 3,
    "template": "approval-request",
    "actionUrl": "/dashboard",
    "metadata": {
      "source": "API"
    }
  },
  {
    "id": "NTF-00024",
    "title": "Compliance document pending",
    "description": "Mismatch detected in GRN",
    "channel": "Email",
    "recipient": "user9@example.com",
    "priority": "Critical",
    "status": "Read",
    "module": "Approval",
    "entityId": "ENT-31960",
    "createdAt": "2026-05-10T12:00:00Z",
    "updatedAt": "2026-05-13T12:00:00Z",
    "scheduledAt": "2026-05-15T12:00:00Z",
    "deliveredAt": "",
    "deliveryAttempts": 3,
    "template": "compliance-reminder",
    "actionUrl": "/dashboard",
    "metadata": {
      "source": "System"
    }
  },
  {
    "id": "NTF-00025",
    "title": "Payment failed",
    "description": "Retry queued for bank gateway",
    "channel": "SMS",
    "recipient": "user16@example.com",
    "priority": "Medium",
    "status": "Read",
    "module": "Approval",
    "entityId": "ENT-48232",
    "createdAt": "2026-05-11T12:00:00Z",
    "updatedAt": "2026-05-13T12:00:00Z",
    "scheduledAt": "2026-05-13T12:00:00Z",
    "deliveredAt": "",
    "deliveryAttempts": 1,
    "template": "workflow-alert",
    "actionUrl": "/dashboard",
    "metadata": {
      "source": "System"
    }
  },
  {
    "id": "NTF-00026",
    "title": "Payment success",
    "description": "Retry queued for bank gateway",
    "channel": "SMS",
    "recipient": "user6@example.com",
    "priority": "High",
    "status": "Unread",
    "module": "Payment",
    "entityId": "ENT-91309",
    "createdAt": "2026-05-07T12:00:00Z",
    "updatedAt": "2026-05-13T12:00:00Z",
    "scheduledAt": "2026-05-12T12:00:00Z",
    "deliveredAt": "2026-05-13T12:00:00Z",
    "deliveryAttempts": 2,
    "template": "approval-request",
    "actionUrl": "/dashboard",
    "metadata": {
      "source": "API"
    }
  },
  {
    "id": "NTF-00027",
    "title": "Compliance document pending",
    "description": "KYC document missing",
    "channel": "Email",
    "recipient": "user21@example.com",
    "priority": "Medium",
    "status": "Failed",
    "module": "Approval",
    "entityId": "ENT-86941",
    "createdAt": "2026-05-12T12:00:00Z",
    "updatedAt": "2026-05-13T12:00:00Z",
    "scheduledAt": "2026-05-09T12:00:00Z",
    "deliveredAt": "2026-05-13T12:00:00Z",
    "deliveryAttempts": 3,
    "template": "workflow-alert",
    "actionUrl": "/dashboard",
    "metadata": {
      "source": "User"
    }
  },
  {
    "id": "NTF-00028",
    "title": "Compliance document pending",
    "description": "Mismatch detected in GRN",
    "channel": "Email",
    "recipient": "user17@example.com",
    "priority": "High",
    "status": "Failed",
    "module": "Approval",
    "entityId": "ENT-68438",
    "createdAt": "2026-05-13T12:00:00Z",
    "updatedAt": "2026-05-11T12:00:00Z",
    "scheduledAt": "2026-05-14T12:00:00Z",
    "deliveredAt": "",
    "deliveryAttempts": 1,
    "template": "payment-summary",
    "actionUrl": "/dashboard",
    "metadata": {
      "source": "API"
    }
  },
  {
    "id": "NTF-00029",
    "title": "Payment success",
    "description": "Payment settled successfully",
    "channel": "SMS",
    "recipient": "user15@example.com",
    "priority": "Low",
    "status": "Unread",
    "module": "Matching",
    "entityId": "ENT-56377",
    "createdAt": "2026-05-07T12:00:00Z",
    "updatedAt": "2026-05-12T12:00:00Z",
    "scheduledAt": "2026-05-14T12:00:00Z",
    "deliveredAt": "2026-05-12T12:00:00Z",
    "deliveryAttempts": 2,
    "template": "workflow-alert",
    "actionUrl": "/dashboard",
    "metadata": {
      "source": "System"
    }
  },
  {
    "id": "NTF-00030",
    "title": "Payment success",
    "description": "Mismatch detected in GRN",
    "channel": "SMS",
    "recipient": "user12@example.com",
    "priority": "Medium",
    "status": "Failed",
    "module": "Invoice",
    "entityId": "ENT-47047",
    "createdAt": "2026-05-09T12:00:00Z",
    "updatedAt": "2026-05-13T12:00:00Z",
    "scheduledAt": "2026-05-14T12:00:00Z",
    "deliveredAt": "",
    "deliveryAttempts": 3,
    "template": "payment-summary",
    "actionUrl": "/dashboard",
    "metadata": {
      "source": "User"
    }
  },
  {
    "id": "NTF-00031",
    "title": "Payment failed",
    "description": "Retry queued for bank gateway",
    "channel": "Email",
    "recipient": "user15@example.com",
    "priority": "Low",
    "status": "Unread",
    "module": "Vendor",
    "entityId": "ENT-18326",
    "createdAt": "2026-05-11T12:00:00Z",
    "updatedAt": "2026-05-12T12:00:00Z",
    "scheduledAt": "2026-05-10T12:00:00Z",
    "deliveredAt": "",
    "deliveryAttempts": 3,
    "template": "payment-summary",
    "actionUrl": "/dashboard",
    "metadata": {
      "source": "API"
    }
  },
  {
    "id": "NTF-00032",
    "title": "Approval escalated",
    "description": "Action required on invoice",
    "channel": "In-app",
    "recipient": "user9@example.com",
    "priority": "Medium",
    "status": "Read",
    "module": "Audit",
    "entityId": "ENT-96187",
    "createdAt": "2026-05-07T12:00:00Z",
    "updatedAt": "2026-05-13T12:00:00Z",
    "scheduledAt": "2026-05-14T12:00:00Z",
    "deliveredAt": "",
    "deliveryAttempts": 2,
    "template": "workflow-alert",
    "actionUrl": "/dashboard",
    "metadata": {
      "source": "System"
    }
  },
  {
    "id": "NTF-00033",
    "title": "Approval escalated",
    "description": "Mismatch detected in GRN",
    "channel": "Email",
    "recipient": "user10@example.com",
    "priority": "Critical",
    "status": "Sent",
    "module": "Invoice",
    "entityId": "ENT-32625",
    "createdAt": "2026-05-13T12:00:00Z",
    "updatedAt": "2026-05-13T12:00:00Z",
    "scheduledAt": "2026-05-14T12:00:00Z",
    "deliveredAt": "",
    "deliveryAttempts": 3,
    "template": "approval-request",
    "actionUrl": "/dashboard",
    "metadata": {
      "source": "System"
    }
  },
  {
    "id": "NTF-00034",
    "title": "Vendor onboarding approved",
    "description": "KYC document missing",
    "channel": "Slack",
    "recipient": "user15@example.com",
    "priority": "Medium",
    "status": "Failed",
    "module": "Payment",
    "entityId": "ENT-89104",
    "createdAt": "2026-05-13T12:00:00Z",
    "updatedAt": "2026-05-11T12:00:00Z",
    "scheduledAt": "2026-05-14T12:00:00Z",
    "deliveredAt": "",
    "deliveryAttempts": 3,
    "template": "workflow-alert",
    "actionUrl": "/dashboard",
    "metadata": {
      "source": "User"
    }
  },
  {
    "id": "NTF-00035",
    "title": "Payment success",
    "description": "Retry queued for bank gateway",
    "channel": "SMS",
    "recipient": "user2@example.com",
    "priority": "Medium",
    "status": "Sent",
    "module": "Matching",
    "entityId": "ENT-24152",
    "createdAt": "2026-05-06T12:00:00Z",
    "updatedAt": "2026-05-11T12:00:00Z",
    "scheduledAt": "2026-05-12T12:00:00Z",
    "deliveredAt": "2026-05-11T12:00:00Z",
    "deliveryAttempts": 3,
    "template": "compliance-reminder",
    "actionUrl": "/dashboard",
    "metadata": {
      "source": "User"
    }
  },
  {
    "id": "NTF-00036",
    "title": "Payment success",
    "description": "Payment settled successfully",
    "channel": "Email",
    "recipient": "user21@example.com",
    "priority": "High",
    "status": "Sent",
    "module": "Audit",
    "entityId": "ENT-73484",
    "createdAt": "2026-05-09T12:00:00Z",
    "updatedAt": "2026-05-12T12:00:00Z",
    "scheduledAt": "2026-05-12T12:00:00Z",
    "deliveredAt": "2026-05-12T12:00:00Z",
    "deliveryAttempts": 3,
    "template": "approval-request",
    "actionUrl": "/dashboard",
    "metadata": {
      "source": "System"
    }
  },
  {
    "id": "NTF-00037",
    "title": "Invoice needs attention",
    "description": "Action required on invoice",
    "channel": "SMS",
    "recipient": "user14@example.com",
    "priority": "Low",
    "status": "Failed",
    "module": "Approval",
    "entityId": "ENT-83898",
    "createdAt": "2026-05-11T12:00:00Z",
    "updatedAt": "2026-05-12T12:00:00Z",
    "scheduledAt": "2026-05-14T12:00:00Z",
    "deliveredAt": "2026-05-11T12:00:00Z",
    "deliveryAttempts": 3,
    "template": "compliance-reminder",
    "actionUrl": "/dashboard",
    "metadata": {
      "source": "API"
    }
  },
  {
    "id": "NTF-00038",
    "title": "3-way match failed",
    "description": "Action required on invoice",
    "channel": "In-app",
    "recipient": "user23@example.com",
    "priority": "Low",
    "status": "Sent",
    "module": "Audit",
    "entityId": "ENT-48141",
    "createdAt": "2026-05-07T12:00:00Z",
    "updatedAt": "2026-05-11T12:00:00Z",
    "scheduledAt": "2026-05-11T12:00:00Z",
    "deliveredAt": "2026-05-13T12:00:00Z",
    "deliveryAttempts": 1,
    "template": "approval-request",
    "actionUrl": "/dashboard",
    "metadata": {
      "source": "System"
    }
  },
  {
    "id": "NTF-00039",
    "title": "Payment failed",
    "description": "Retry queued for bank gateway",
    "channel": "In-app",
    "recipient": "user6@example.com",
    "priority": "Low",
    "status": "Read",
    "module": "Vendor",
    "entityId": "ENT-21748",
    "createdAt": "2026-05-08T12:00:00Z",
    "updatedAt": "2026-05-11T12:00:00Z",
    "scheduledAt": "2026-05-09T12:00:00Z",
    "deliveredAt": "",
    "deliveryAttempts": 2,
    "template": "workflow-alert",
    "actionUrl": "/dashboard",
    "metadata": {
      "source": "System"
    }
  },
  {
    "id": "NTF-00040",
    "title": "Compliance document pending",
    "description": "Action required on invoice",
    "channel": "In-app",
    "recipient": "user10@example.com",
    "priority": "High",
    "status": "Unread",
    "module": "Invoice",
    "entityId": "ENT-29797",
    "createdAt": "2026-05-08T12:00:00Z",
    "updatedAt": "2026-05-12T12:00:00Z",
    "scheduledAt": "2026-05-09T12:00:00Z",
    "deliveredAt": "",
    "deliveryAttempts": 3,
    "template": "workflow-alert",
    "actionUrl": "/dashboard",
    "metadata": {
      "source": "System"
    }
  },
  {
    "id": "NTF-00041",
    "title": "Payment success",
    "description": "Action required on invoice",
    "channel": "In-app",
    "recipient": "user1@example.com",
    "priority": "High",
    "status": "Sent",
    "module": "Vendor",
    "entityId": "ENT-87460",
    "createdAt": "2026-05-07T12:00:00Z",
    "updatedAt": "2026-05-11T12:00:00Z",
    "scheduledAt": "2026-05-14T12:00:00Z",
    "deliveredAt": "2026-05-13T12:00:00Z",
    "deliveryAttempts": 3,
    "template": "approval-request",
    "actionUrl": "/dashboard",
    "metadata": {
      "source": "API"
    }
  },
  {
    "id": "NTF-00042",
    "title": "Payment failed",
    "description": "KYC document missing",
    "channel": "Slack",
    "recipient": "user9@example.com",
    "priority": "Medium",
    "status": "Unread",
    "module": "Audit",
    "entityId": "ENT-46076",
    "createdAt": "2026-05-08T12:00:00Z",
    "updatedAt": "2026-05-12T12:00:00Z",
    "scheduledAt": "2026-05-11T12:00:00Z",
    "deliveredAt": "2026-05-12T12:00:00Z",
    "deliveryAttempts": 2,
    "template": "payment-summary",
    "actionUrl": "/dashboard",
    "metadata": {
      "source": "API"
    }
  },
  {
    "id": "NTF-00043",
    "title": "Payment failed",
    "description": "Action required on invoice",
    "channel": "In-app",
    "recipient": "user24@example.com",
    "priority": "Medium",
    "status": "Read",
    "module": "Audit",
    "entityId": "ENT-32473",
    "createdAt": "2026-05-13T12:00:00Z",
    "updatedAt": "2026-05-13T12:00:00Z",
    "scheduledAt": "2026-05-13T12:00:00Z",
    "deliveredAt": "2026-05-12T12:00:00Z",
    "deliveryAttempts": 2,
    "template": "compliance-reminder",
    "actionUrl": "/dashboard",
    "metadata": {
      "source": "System"
    }
  },
  {
    "id": "NTF-00044",
    "title": "3-way match failed",
    "description": "Action required on invoice",
    "channel": "In-app",
    "recipient": "user5@example.com",
    "priority": "Low",
    "status": "Unread",
    "module": "Invoice",
    "entityId": "ENT-79710",
    "createdAt": "2026-05-07T12:00:00Z",
    "updatedAt": "2026-05-11T12:00:00Z",
    "scheduledAt": "2026-05-14T12:00:00Z",
    "deliveredAt": "2026-05-13T12:00:00Z",
    "deliveryAttempts": 2,
    "template": "workflow-alert",
    "actionUrl": "/dashboard",
    "metadata": {
      "source": "API"
    }
  },
  {
    "id": "NTF-00045",
    "title": "Invoice needs attention",
    "description": "KYC document missing",
    "channel": "Slack",
    "recipient": "user9@example.com",
    "priority": "Critical",
    "status": "Failed",
    "module": "Vendor",
    "entityId": "ENT-23089",
    "createdAt": "2026-05-13T12:00:00Z",
    "updatedAt": "2026-05-11T12:00:00Z",
    "scheduledAt": "2026-05-10T12:00:00Z",
    "deliveredAt": "2026-05-12T12:00:00Z",
    "deliveryAttempts": 2,
    "template": "approval-request",
    "actionUrl": "/dashboard",
    "metadata": {
      "source": "User"
    }
  },
  {
    "id": "NTF-00046",
    "title": "Payment success",
    "description": "Mismatch detected in GRN",
    "channel": "SMS",
    "recipient": "user3@example.com",
    "priority": "Medium",
    "status": "Sent",
    "module": "Matching",
    "entityId": "ENT-69576",
    "createdAt": "2026-05-10T12:00:00Z",
    "updatedAt": "2026-05-12T12:00:00Z",
    "scheduledAt": "2026-05-14T12:00:00Z",
    "deliveredAt": "2026-05-11T12:00:00Z",
    "deliveryAttempts": 1,
    "template": "compliance-reminder",
    "actionUrl": "/dashboard",
    "metadata": {
      "source": "User"
    }
  },
  {
    "id": "NTF-00047",
    "title": "Approval escalated",
    "description": "Payment settled successfully",
    "channel": "Slack",
    "recipient": "user12@example.com",
    "priority": "Medium",
    "status": "Sent",
    "module": "Approval",
    "entityId": "ENT-78163",
    "createdAt": "2026-05-09T12:00:00Z",
    "updatedAt": "2026-05-13T12:00:00Z",
    "scheduledAt": "2026-05-11T12:00:00Z",
    "deliveredAt": "",
    "deliveryAttempts": 1,
    "template": "payment-summary",
    "actionUrl": "/dashboard",
    "metadata": {
      "source": "API"
    }
  },
  {
    "id": "NTF-00048",
    "title": "Payment failed",
    "description": "KYC document missing",
    "channel": "SMS",
    "recipient": "user18@example.com",
    "priority": "Low",
    "status": "Sent",
    "module": "Payment",
    "entityId": "ENT-19890",
    "createdAt": "2026-05-09T12:00:00Z",
    "updatedAt": "2026-05-11T12:00:00Z",
    "scheduledAt": "2026-05-13T12:00:00Z",
    "deliveredAt": "",
    "deliveryAttempts": 2,
    "template": "payment-summary",
    "actionUrl": "/dashboard",
    "metadata": {
      "source": "User"
    }
  },
  {
    "id": "NTF-00049",
    "title": "Approval escalated",
    "description": "Action required on invoice",
    "channel": "In-app",
    "recipient": "user8@example.com",
    "priority": "Medium",
    "status": "Unread",
    "module": "Matching",
    "entityId": "ENT-46605",
    "createdAt": "2026-05-07T12:00:00Z",
    "updatedAt": "2026-05-12T12:00:00Z",
    "scheduledAt": "2026-05-14T12:00:00Z",
    "deliveredAt": "2026-05-11T12:00:00Z",
    "deliveryAttempts": 3,
    "template": "compliance-reminder",
    "actionUrl": "/dashboard",
    "metadata": {
      "source": "User"
    }
  },
  {
    "id": "NTF-00050",
    "title": "Compliance document pending",
    "description": "Action required on invoice",
    "channel": "Email",
    "recipient": "user10@example.com",
    "priority": "High",
    "status": "Read",
    "module": "Approval",
    "entityId": "ENT-35057",
    "createdAt": "2026-05-10T12:00:00Z",
    "updatedAt": "2026-05-13T12:00:00Z",
    "scheduledAt": "2026-05-15T12:00:00Z",
    "deliveredAt": "",
    "deliveryAttempts": 1,
    "template": "compliance-reminder",
    "actionUrl": "/dashboard",
    "metadata": {
      "source": "API"
    }
  },
  {
    "id": "NTF-00051",
    "title": "Payment failed",
    "description": "Action required on invoice",
    "channel": "In-app",
    "recipient": "user8@example.com",
    "priority": "High",
    "status": "Read",
    "module": "Payment",
    "entityId": "ENT-64903",
    "createdAt": "2026-05-09T12:00:00Z",
    "updatedAt": "2026-05-12T12:00:00Z",
    "scheduledAt": "2026-05-13T12:00:00Z",
    "deliveredAt": "2026-05-13T12:00:00Z",
    "deliveryAttempts": 2,
    "template": "approval-request",
    "actionUrl": "/dashboard",
    "metadata": {
      "source": "API"
    }
  },
  {
    "id": "NTF-00052",
    "title": "Payment failed",
    "description": "Action required on invoice",
    "channel": "Email",
    "recipient": "user21@example.com",
    "priority": "Low",
    "status": "Failed",
    "module": "Matching",
    "entityId": "ENT-64672",
    "createdAt": "2026-05-11T12:00:00Z",
    "updatedAt": "2026-05-13T12:00:00Z",
    "scheduledAt": "2026-05-15T12:00:00Z",
    "deliveredAt": "",
    "deliveryAttempts": 3,
    "template": "workflow-alert",
    "actionUrl": "/dashboard",
    "metadata": {
      "source": "API"
    }
  },
  {
    "id": "NTF-00053",
    "title": "3-way match failed",
    "description": "Retry queued for bank gateway",
    "channel": "In-app",
    "recipient": "user1@example.com",
    "priority": "Low",
    "status": "Read",
    "module": "Invoice",
    "entityId": "ENT-91117",
    "createdAt": "2026-05-06T12:00:00Z",
    "updatedAt": "2026-05-13T12:00:00Z",
    "scheduledAt": "2026-05-13T12:00:00Z",
    "deliveredAt": "2026-05-13T12:00:00Z",
    "deliveryAttempts": 1,
    "template": "compliance-reminder",
    "actionUrl": "/dashboard",
    "metadata": {
      "source": "System"
    }
  },
  {
    "id": "NTF-00054",
    "title": "Invoice needs attention",
    "description": "KYC document missing",
    "channel": "Email",
    "recipient": "user9@example.com",
    "priority": "Medium",
    "status": "Failed",
    "module": "Invoice",
    "entityId": "ENT-56999",
    "createdAt": "2026-05-07T12:00:00Z",
    "updatedAt": "2026-05-12T12:00:00Z",
    "scheduledAt": "2026-05-13T12:00:00Z",
    "deliveredAt": "2026-05-12T12:00:00Z",
    "deliveryAttempts": 3,
    "template": "approval-request",
    "actionUrl": "/dashboard",
    "metadata": {
      "source": "System"
    }
  },
  {
    "id": "NTF-00055",
    "title": "3-way match failed",
    "description": "Action required on invoice",
    "channel": "SMS",
    "recipient": "user24@example.com",
    "priority": "Critical",
    "status": "Read",
    "module": "Payment",
    "entityId": "ENT-35072",
    "createdAt": "2026-05-06T12:00:00Z",
    "updatedAt": "2026-05-11T12:00:00Z",
    "scheduledAt": "2026-05-09T12:00:00Z",
    "deliveredAt": "2026-05-13T12:00:00Z",
    "deliveryAttempts": 1,
    "template": "approval-request",
    "actionUrl": "/dashboard",
    "metadata": {
      "source": "System"
    }
  },
  {
    "id": "NTF-00056",
    "title": "Invoice needs attention",
    "description": "Payment settled successfully",
    "channel": "Slack",
    "recipient": "user7@example.com",
    "priority": "Critical",
    "status": "Sent",
    "module": "Invoice",
    "entityId": "ENT-79941",
    "createdAt": "2026-05-10T12:00:00Z",
    "updatedAt": "2026-05-13T12:00:00Z",
    "scheduledAt": "2026-05-13T12:00:00Z",
    "deliveredAt": "",
    "deliveryAttempts": 3,
    "template": "compliance-reminder",
    "actionUrl": "/dashboard",
    "metadata": {
      "source": "API"
    }
  },
  {
    "id": "NTF-00057",
    "title": "Payment success",
    "description": "Payment settled successfully",
    "channel": "In-app",
    "recipient": "user25@example.com",
    "priority": "Critical",
    "status": "Read",
    "module": "Payment",
    "entityId": "ENT-97817",
    "createdAt": "2026-05-06T12:00:00Z",
    "updatedAt": "2026-05-13T12:00:00Z",
    "scheduledAt": "2026-05-12T12:00:00Z",
    "deliveredAt": "",
    "deliveryAttempts": 1,
    "template": "payment-summary",
    "actionUrl": "/dashboard",
    "metadata": {
      "source": "API"
    }
  },
  {
    "id": "NTF-00058",
    "title": "Payment success",
    "description": "Action required on invoice",
    "channel": "In-app",
    "recipient": "user5@example.com",
    "priority": "Low",
    "status": "Failed",
    "module": "Approval",
    "entityId": "ENT-12045",
    "createdAt": "2026-05-11T12:00:00Z",
    "updatedAt": "2026-05-13T12:00:00Z",
    "scheduledAt": "2026-05-15T12:00:00Z",
    "deliveredAt": "",
    "deliveryAttempts": 1,
    "template": "compliance-reminder",
    "actionUrl": "/dashboard",
    "metadata": {
      "source": "API"
    }
  },
  {
    "id": "NTF-00059",
    "title": "Payment failed",
    "description": "Action required on invoice",
    "channel": "In-app",
    "recipient": "user17@example.com",
    "priority": "High",
    "status": "Read",
    "module": "Invoice",
    "entityId": "ENT-72759",
    "createdAt": "2026-05-10T12:00:00Z",
    "updatedAt": "2026-05-11T12:00:00Z",
    "scheduledAt": "2026-05-13T12:00:00Z",
    "deliveredAt": "2026-05-12T12:00:00Z",
    "deliveryAttempts": 3,
    "template": "workflow-alert",
    "actionUrl": "/dashboard",
    "metadata": {
      "source": "System"
    }
  },
  {
    "id": "NTF-00060",
    "title": "Payment failed",
    "description": "Payment settled successfully",
    "channel": "In-app",
    "recipient": "user4@example.com",
    "priority": "High",
    "status": "Unread",
    "module": "Vendor",
    "entityId": "ENT-45066",
    "createdAt": "2026-05-08T12:00:00Z",
    "updatedAt": "2026-05-11T12:00:00Z",
    "scheduledAt": "2026-05-14T12:00:00Z",
    "deliveredAt": "2026-05-13T12:00:00Z",
    "deliveryAttempts": 1,
    "template": "compliance-reminder",
    "actionUrl": "/dashboard",
    "metadata": {
      "source": "API"
    }
  },
  {
    "id": "NTF-00061",
    "title": "Vendor onboarding approved",
    "description": "KYC document missing",
    "channel": "In-app",
    "recipient": "user13@example.com",
    "priority": "Critical",
    "status": "Unread",
    "module": "Matching",
    "entityId": "ENT-79991",
    "createdAt": "2026-05-10T12:00:00Z",
    "updatedAt": "2026-05-12T12:00:00Z",
    "scheduledAt": "2026-05-14T12:00:00Z",
    "deliveredAt": "",
    "deliveryAttempts": 3,
    "template": "payment-summary",
    "actionUrl": "/dashboard",
    "metadata": {
      "source": "System"
    }
  },
  {
    "id": "NTF-00062",
    "title": "Compliance document pending",
    "description": "Action required on invoice",
    "channel": "In-app",
    "recipient": "user3@example.com",
    "priority": "Low",
    "status": "Read",
    "module": "Audit",
    "entityId": "ENT-16151",
    "createdAt": "2026-05-07T12:00:00Z",
    "updatedAt": "2026-05-11T12:00:00Z",
    "scheduledAt": "2026-05-13T12:00:00Z",
    "deliveredAt": "",
    "deliveryAttempts": 2,
    "template": "approval-request",
    "actionUrl": "/dashboard",
    "metadata": {
      "source": "API"
    }
  },
  {
    "id": "NTF-00063",
    "title": "Invoice needs attention",
    "description": "Action required on invoice",
    "channel": "Email",
    "recipient": "user15@example.com",
    "priority": "Critical",
    "status": "Sent",
    "module": "Vendor",
    "entityId": "ENT-71774",
    "createdAt": "2026-05-08T12:00:00Z",
    "updatedAt": "2026-05-13T12:00:00Z",
    "scheduledAt": "2026-05-11T12:00:00Z",
    "deliveredAt": "",
    "deliveryAttempts": 2,
    "template": "compliance-reminder",
    "actionUrl": "/dashboard",
    "metadata": {
      "source": "System"
    }
  },
  {
    "id": "NTF-00064",
    "title": "Approval escalated",
    "description": "Payment settled successfully",
    "channel": "In-app",
    "recipient": "user15@example.com",
    "priority": "Low",
    "status": "Failed",
    "module": "Vendor",
    "entityId": "ENT-46456",
    "createdAt": "2026-05-06T12:00:00Z",
    "updatedAt": "2026-05-13T12:00:00Z",
    "scheduledAt": "2026-05-14T12:00:00Z",
    "deliveredAt": "",
    "deliveryAttempts": 2,
    "template": "payment-summary",
    "actionUrl": "/dashboard",
    "metadata": {
      "source": "API"
    }
  },
  {
    "id": "NTF-00065",
    "title": "3-way match failed",
    "description": "Mismatch detected in GRN",
    "channel": "SMS",
    "recipient": "user16@example.com",
    "priority": "Critical",
    "status": "Read",
    "module": "Invoice",
    "entityId": "ENT-10291",
    "createdAt": "2026-05-12T12:00:00Z",
    "updatedAt": "2026-05-11T12:00:00Z",
    "scheduledAt": "2026-05-09T12:00:00Z",
    "deliveredAt": "",
    "deliveryAttempts": 2,
    "template": "approval-request",
    "actionUrl": "/dashboard",
    "metadata": {
      "source": "System"
    }
  },
  {
    "id": "NTF-00066",
    "title": "Payment success",
    "description": "Action required on invoice",
    "channel": "Email",
    "recipient": "user16@example.com",
    "priority": "High",
    "status": "Read",
    "module": "Payment",
    "entityId": "ENT-81893",
    "createdAt": "2026-05-07T12:00:00Z",
    "updatedAt": "2026-05-13T12:00:00Z",
    "scheduledAt": "2026-05-13T12:00:00Z",
    "deliveredAt": "2026-05-12T12:00:00Z",
    "deliveryAttempts": 3,
    "template": "payment-summary",
    "actionUrl": "/dashboard",
    "metadata": {
      "source": "API"
    }
  },
  {
    "id": "NTF-00067",
    "title": "Invoice needs attention",
    "description": "Action required on invoice",
    "channel": "SMS",
    "recipient": "user14@example.com",
    "priority": "Low",
    "status": "Read",
    "module": "Audit",
    "entityId": "ENT-61756",
    "createdAt": "2026-05-10T12:00:00Z",
    "updatedAt": "2026-05-13T12:00:00Z",
    "scheduledAt": "2026-05-11T12:00:00Z",
    "deliveredAt": "2026-05-11T12:00:00Z",
    "deliveryAttempts": 2,
    "template": "payment-summary",
    "actionUrl": "/dashboard",
    "metadata": {
      "source": "User"
    }
  },
  {
    "id": "NTF-00068",
    "title": "Approval escalated",
    "description": "Payment settled successfully",
    "channel": "SMS",
    "recipient": "user24@example.com",
    "priority": "Critical",
    "status": "Sent",
    "module": "Invoice",
    "entityId": "ENT-85331",
    "createdAt": "2026-05-11T12:00:00Z",
    "updatedAt": "2026-05-13T12:00:00Z",
    "scheduledAt": "2026-05-11T12:00:00Z",
    "deliveredAt": "",
    "deliveryAttempts": 3,
    "template": "payment-summary",
    "actionUrl": "/dashboard",
    "metadata": {
      "source": "API"
    }
  },
  {
    "id": "NTF-00069",
    "title": "Vendor onboarding approved",
    "description": "Action required on invoice",
    "channel": "Slack",
    "recipient": "user12@example.com",
    "priority": "Medium",
    "status": "Read",
    "module": "Approval",
    "entityId": "ENT-42047",
    "createdAt": "2026-05-12T12:00:00Z",
    "updatedAt": "2026-05-13T12:00:00Z",
    "scheduledAt": "2026-05-15T12:00:00Z",
    "deliveredAt": "2026-05-12T12:00:00Z",
    "deliveryAttempts": 1,
    "template": "workflow-alert",
    "actionUrl": "/dashboard",
    "metadata": {
      "source": "API"
    }
  },
  {
    "id": "NTF-00070",
    "title": "Approval escalated",
    "description": "Payment settled successfully",
    "channel": "Slack",
    "recipient": "user5@example.com",
    "priority": "Medium",
    "status": "Failed",
    "module": "Approval",
    "entityId": "ENT-88272",
    "createdAt": "2026-05-09T12:00:00Z",
    "updatedAt": "2026-05-13T12:00:00Z",
    "scheduledAt": "2026-05-09T12:00:00Z",
    "deliveredAt": "2026-05-12T12:00:00Z",
    "deliveryAttempts": 1,
    "template": "workflow-alert",
    "actionUrl": "/dashboard",
    "metadata": {
      "source": "System"
    }
  },
  {
    "id": "NTF-00071",
    "title": "Vendor onboarding approved",
    "description": "Payment settled successfully",
    "channel": "Email",
    "recipient": "user17@example.com",
    "priority": "High",
    "status": "Sent",
    "module": "Matching",
    "entityId": "ENT-53909",
    "createdAt": "2026-05-09T12:00:00Z",
    "updatedAt": "2026-05-13T12:00:00Z",
    "scheduledAt": "2026-05-11T12:00:00Z",
    "deliveredAt": "2026-05-11T12:00:00Z",
    "deliveryAttempts": 3,
    "template": "approval-request",
    "actionUrl": "/dashboard",
    "metadata": {
      "source": "System"
    }
  },
  {
    "id": "NTF-00072",
    "title": "Approval escalated",
    "description": "KYC document missing",
    "channel": "In-app",
    "recipient": "user9@example.com",
    "priority": "Critical",
    "status": "Failed",
    "module": "Matching",
    "entityId": "ENT-22677",
    "createdAt": "2026-05-12T12:00:00Z",
    "updatedAt": "2026-05-12T12:00:00Z",
    "scheduledAt": "2026-05-11T12:00:00Z",
    "deliveredAt": "2026-05-13T12:00:00Z",
    "deliveryAttempts": 1,
    "template": "approval-request",
    "actionUrl": "/dashboard",
    "metadata": {
      "source": "API"
    }
  },
  {
    "id": "NTF-00073",
    "title": "Compliance document pending",
    "description": "Mismatch detected in GRN",
    "channel": "SMS",
    "recipient": "user13@example.com",
    "priority": "Critical",
    "status": "Failed",
    "module": "Payment",
    "entityId": "ENT-59086",
    "createdAt": "2026-05-07T12:00:00Z",
    "updatedAt": "2026-05-12T12:00:00Z",
    "scheduledAt": "2026-05-10T12:00:00Z",
    "deliveredAt": "2026-05-13T12:00:00Z",
    "deliveryAttempts": 2,
    "template": "payment-summary",
    "actionUrl": "/dashboard",
    "metadata": {
      "source": "User"
    }
  },
  {
    "id": "NTF-00074",
    "title": "Payment failed",
    "description": "Payment settled successfully",
    "channel": "Slack",
    "recipient": "user24@example.com",
    "priority": "Critical",
    "status": "Read",
    "module": "Matching",
    "entityId": "ENT-71821",
    "createdAt": "2026-05-10T12:00:00Z",
    "updatedAt": "2026-05-11T12:00:00Z",
    "scheduledAt": "2026-05-11T12:00:00Z",
    "deliveredAt": "2026-05-13T12:00:00Z",
    "deliveryAttempts": 2,
    "template": "compliance-reminder",
    "actionUrl": "/dashboard",
    "metadata": {
      "source": "User"
    }
  },
  {
    "id": "NTF-00075",
    "title": "Approval escalated",
    "description": "Retry queued for bank gateway",
    "channel": "In-app",
    "recipient": "user22@example.com",
    "priority": "Low",
    "status": "Unread",
    "module": "Invoice",
    "entityId": "ENT-94068",
    "createdAt": "2026-05-07T12:00:00Z",
    "updatedAt": "2026-05-12T12:00:00Z",
    "scheduledAt": "2026-05-13T12:00:00Z",
    "deliveredAt": "2026-05-12T12:00:00Z",
    "deliveryAttempts": 2,
    "template": "payment-summary",
    "actionUrl": "/dashboard",
    "metadata": {
      "source": "User"
    }
  },
  {
    "id": "NTF-00076",
    "title": "Approval escalated",
    "description": "Retry queued for bank gateway",
    "channel": "SMS",
    "recipient": "user13@example.com",
    "priority": "High",
    "status": "Read",
    "module": "Approval",
    "entityId": "ENT-55805",
    "createdAt": "2026-05-11T12:00:00Z",
    "updatedAt": "2026-05-12T12:00:00Z",
    "scheduledAt": "2026-05-10T12:00:00Z",
    "deliveredAt": "2026-05-11T12:00:00Z",
    "deliveryAttempts": 2,
    "template": "approval-request",
    "actionUrl": "/dashboard",
    "metadata": {
      "source": "API"
    }
  },
  {
    "id": "NTF-00077",
    "title": "Compliance document pending",
    "description": "Mismatch detected in GRN",
    "channel": "SMS",
    "recipient": "user22@example.com",
    "priority": "High",
    "status": "Read",
    "module": "Invoice",
    "entityId": "ENT-36209",
    "createdAt": "2026-05-11T12:00:00Z",
    "updatedAt": "2026-05-11T12:00:00Z",
    "scheduledAt": "2026-05-09T12:00:00Z",
    "deliveredAt": "",
    "deliveryAttempts": 1,
    "template": "workflow-alert",
    "actionUrl": "/dashboard",
    "metadata": {
      "source": "System"
    }
  },
  {
    "id": "NTF-00078",
    "title": "Invoice needs attention",
    "description": "Payment settled successfully",
    "channel": "SMS",
    "recipient": "user10@example.com",
    "priority": "Critical",
    "status": "Unread",
    "module": "Approval",
    "entityId": "ENT-56269",
    "createdAt": "2026-05-10T12:00:00Z",
    "updatedAt": "2026-05-11T12:00:00Z",
    "scheduledAt": "2026-05-11T12:00:00Z",
    "deliveredAt": "",
    "deliveryAttempts": 2,
    "template": "workflow-alert",
    "actionUrl": "/dashboard",
    "metadata": {
      "source": "System"
    }
  },
  {
    "id": "NTF-00079",
    "title": "Compliance document pending",
    "description": "KYC document missing",
    "channel": "SMS",
    "recipient": "user23@example.com",
    "priority": "Medium",
    "status": "Failed",
    "module": "Payment",
    "entityId": "ENT-96998",
    "createdAt": "2026-05-06T12:00:00Z",
    "updatedAt": "2026-05-13T12:00:00Z",
    "scheduledAt": "2026-05-12T12:00:00Z",
    "deliveredAt": "",
    "deliveryAttempts": 2,
    "template": "payment-summary",
    "actionUrl": "/dashboard",
    "metadata": {
      "source": "User"
    }
  },
  {
    "id": "NTF-00080",
    "title": "Vendor onboarding approved",
    "description": "Action required on invoice",
    "channel": "Email",
    "recipient": "user12@example.com",
    "priority": "Medium",
    "status": "Unread",
    "module": "Matching",
    "entityId": "ENT-64442",
    "createdAt": "2026-05-13T12:00:00Z",
    "updatedAt": "2026-05-12T12:00:00Z",
    "scheduledAt": "2026-05-11T12:00:00Z",
    "deliveredAt": "2026-05-12T12:00:00Z",
    "deliveryAttempts": 1,
    "template": "compliance-reminder",
    "actionUrl": "/dashboard",
    "metadata": {
      "source": "User"
    }
  },
  {
    "id": "NTF-00081",
    "title": "3-way match failed",
    "description": "KYC document missing",
    "channel": "Email",
    "recipient": "user13@example.com",
    "priority": "High",
    "status": "Unread",
    "module": "Payment",
    "entityId": "ENT-73255",
    "createdAt": "2026-05-10T12:00:00Z",
    "updatedAt": "2026-05-11T12:00:00Z",
    "scheduledAt": "2026-05-15T12:00:00Z",
    "deliveredAt": "2026-05-12T12:00:00Z",
    "deliveryAttempts": 1,
    "template": "workflow-alert",
    "actionUrl": "/dashboard",
    "metadata": {
      "source": "User"
    }
  },
  {
    "id": "NTF-00082",
    "title": "Approval escalated",
    "description": "Payment settled successfully",
    "channel": "In-app",
    "recipient": "user3@example.com",
    "priority": "Low",
    "status": "Failed",
    "module": "Invoice",
    "entityId": "ENT-23939",
    "createdAt": "2026-05-09T12:00:00Z",
    "updatedAt": "2026-05-12T12:00:00Z",
    "scheduledAt": "2026-05-15T12:00:00Z",
    "deliveredAt": "2026-05-13T12:00:00Z",
    "deliveryAttempts": 1,
    "template": "approval-request",
    "actionUrl": "/dashboard",
    "metadata": {
      "source": "API"
    }
  },
  {
    "id": "NTF-00083",
    "title": "Payment failed",
    "description": "Action required on invoice",
    "channel": "Email",
    "recipient": "user23@example.com",
    "priority": "Medium",
    "status": "Read",
    "module": "Invoice",
    "entityId": "ENT-84012",
    "createdAt": "2026-05-12T12:00:00Z",
    "updatedAt": "2026-05-11T12:00:00Z",
    "scheduledAt": "2026-05-15T12:00:00Z",
    "deliveredAt": "2026-05-12T12:00:00Z",
    "deliveryAttempts": 3,
    "template": "approval-request",
    "actionUrl": "/dashboard",
    "metadata": {
      "source": "User"
    }
  },
  {
    "id": "NTF-00084",
    "title": "Approval escalated",
    "description": "Retry queued for bank gateway",
    "channel": "SMS",
    "recipient": "user9@example.com",
    "priority": "Low",
    "status": "Read",
    "module": "Invoice",
    "entityId": "ENT-47027",
    "createdAt": "2026-05-10T12:00:00Z",
    "updatedAt": "2026-05-12T12:00:00Z",
    "scheduledAt": "2026-05-13T12:00:00Z",
    "deliveredAt": "",
    "deliveryAttempts": 3,
    "template": "workflow-alert",
    "actionUrl": "/dashboard",
    "metadata": {
      "source": "API"
    }
  },
  {
    "id": "NTF-00085",
    "title": "Payment success",
    "description": "Mismatch detected in GRN",
    "channel": "Slack",
    "recipient": "user9@example.com",
    "priority": "Medium",
    "status": "Unread",
    "module": "Payment",
    "entityId": "ENT-76337",
    "createdAt": "2026-05-11T12:00:00Z",
    "updatedAt": "2026-05-11T12:00:00Z",
    "scheduledAt": "2026-05-13T12:00:00Z",
    "deliveredAt": "2026-05-11T12:00:00Z",
    "deliveryAttempts": 2,
    "template": "compliance-reminder",
    "actionUrl": "/dashboard",
    "metadata": {
      "source": "User"
    }
  },
  {
    "id": "NTF-00086",
    "title": "Invoice needs attention",
    "description": "Action required on invoice",
    "channel": "Email",
    "recipient": "user19@example.com",
    "priority": "Low",
    "status": "Sent",
    "module": "Matching",
    "entityId": "ENT-33868",
    "createdAt": "2026-05-09T12:00:00Z",
    "updatedAt": "2026-05-11T12:00:00Z",
    "scheduledAt": "2026-05-13T12:00:00Z",
    "deliveredAt": "2026-05-12T12:00:00Z",
    "deliveryAttempts": 2,
    "template": "workflow-alert",
    "actionUrl": "/dashboard",
    "metadata": {
      "source": "User"
    }
  },
  {
    "id": "NTF-00087",
    "title": "Invoice needs attention",
    "description": "KYC document missing",
    "channel": "Email",
    "recipient": "user11@example.com",
    "priority": "High",
    "status": "Sent",
    "module": "Audit",
    "entityId": "ENT-20966",
    "createdAt": "2026-05-09T12:00:00Z",
    "updatedAt": "2026-05-12T12:00:00Z",
    "scheduledAt": "2026-05-10T12:00:00Z",
    "deliveredAt": "2026-05-13T12:00:00Z",
    "deliveryAttempts": 3,
    "template": "workflow-alert",
    "actionUrl": "/dashboard",
    "metadata": {
      "source": "System"
    }
  },
  {
    "id": "NTF-00088",
    "title": "3-way match failed",
    "description": "Retry queued for bank gateway",
    "channel": "Slack",
    "recipient": "user9@example.com",
    "priority": "High",
    "status": "Read",
    "module": "Approval",
    "entityId": "ENT-38985",
    "createdAt": "2026-05-06T12:00:00Z",
    "updatedAt": "2026-05-13T12:00:00Z",
    "scheduledAt": "2026-05-10T12:00:00Z",
    "deliveredAt": "2026-05-12T12:00:00Z",
    "deliveryAttempts": 2,
    "template": "compliance-reminder",
    "actionUrl": "/dashboard",
    "metadata": {
      "source": "System"
    }
  },
  {
    "id": "NTF-00089",
    "title": "Payment failed",
    "description": "Retry queued for bank gateway",
    "channel": "SMS",
    "recipient": "user15@example.com",
    "priority": "Low",
    "status": "Unread",
    "module": "Invoice",
    "entityId": "ENT-87868",
    "createdAt": "2026-05-07T12:00:00Z",
    "updatedAt": "2026-05-13T12:00:00Z",
    "scheduledAt": "2026-05-14T12:00:00Z",
    "deliveredAt": "",
    "deliveryAttempts": 2,
    "template": "approval-request",
    "actionUrl": "/dashboard",
    "metadata": {
      "source": "System"
    }
  },
  {
    "id": "NTF-00090",
    "title": "Approval escalated",
    "description": "Payment settled successfully",
    "channel": "In-app",
    "recipient": "user9@example.com",
    "priority": "Medium",
    "status": "Unread",
    "module": "Matching",
    "entityId": "ENT-32593",
    "createdAt": "2026-05-07T12:00:00Z",
    "updatedAt": "2026-05-11T12:00:00Z",
    "scheduledAt": "2026-05-13T12:00:00Z",
    "deliveredAt": "2026-05-13T12:00:00Z",
    "deliveryAttempts": 2,
    "template": "approval-request",
    "actionUrl": "/dashboard",
    "metadata": {
      "source": "API"
    }
  },
  {
    "id": "NTF-00091",
    "title": "Payment success",
    "description": "Mismatch detected in GRN",
    "channel": "Slack",
    "recipient": "user1@example.com",
    "priority": "Low",
    "status": "Unread",
    "module": "Audit",
    "entityId": "ENT-49012",
    "createdAt": "2026-05-07T12:00:00Z",
    "updatedAt": "2026-05-11T12:00:00Z",
    "scheduledAt": "2026-05-14T12:00:00Z",
    "deliveredAt": "",
    "deliveryAttempts": 2,
    "template": "compliance-reminder",
    "actionUrl": "/dashboard",
    "metadata": {
      "source": "User"
    }
  },
  {
    "id": "NTF-00092",
    "title": "Payment success",
    "description": "KYC document missing",
    "channel": "Slack",
    "recipient": "user9@example.com",
    "priority": "High",
    "status": "Failed",
    "module": "Payment",
    "entityId": "ENT-23350",
    "createdAt": "2026-05-13T12:00:00Z",
    "updatedAt": "2026-05-13T12:00:00Z",
    "scheduledAt": "2026-05-14T12:00:00Z",
    "deliveredAt": "",
    "deliveryAttempts": 1,
    "template": "approval-request",
    "actionUrl": "/dashboard",
    "metadata": {
      "source": "User"
    }
  },
  {
    "id": "NTF-00093",
    "title": "Payment success",
    "description": "KYC document missing",
    "channel": "Email",
    "recipient": "user21@example.com",
    "priority": "Critical",
    "status": "Read",
    "module": "Approval",
    "entityId": "ENT-18745",
    "createdAt": "2026-05-06T12:00:00Z",
    "updatedAt": "2026-05-11T12:00:00Z",
    "scheduledAt": "2026-05-15T12:00:00Z",
    "deliveredAt": "2026-05-13T12:00:00Z",
    "deliveryAttempts": 3,
    "template": "compliance-reminder",
    "actionUrl": "/dashboard",
    "metadata": {
      "source": "System"
    }
  },
  {
    "id": "NTF-00094",
    "title": "Payment failed",
    "description": "Retry queued for bank gateway",
    "channel": "SMS",
    "recipient": "user19@example.com",
    "priority": "High",
    "status": "Read",
    "module": "Matching",
    "entityId": "ENT-31628",
    "createdAt": "2026-05-10T12:00:00Z",
    "updatedAt": "2026-05-13T12:00:00Z",
    "scheduledAt": "2026-05-15T12:00:00Z",
    "deliveredAt": "2026-05-13T12:00:00Z",
    "deliveryAttempts": 3,
    "template": "workflow-alert",
    "actionUrl": "/dashboard",
    "metadata": {
      "source": "User"
    }
  },
  {
    "id": "NTF-00095",
    "title": "Payment failed",
    "description": "Payment settled successfully",
    "channel": "Slack",
    "recipient": "user22@example.com",
    "priority": "Critical",
    "status": "Failed",
    "module": "Matching",
    "entityId": "ENT-50182",
    "createdAt": "2026-05-08T12:00:00Z",
    "updatedAt": "2026-05-12T12:00:00Z",
    "scheduledAt": "2026-05-12T12:00:00Z",
    "deliveredAt": "2026-05-13T12:00:00Z",
    "deliveryAttempts": 3,
    "template": "payment-summary",
    "actionUrl": "/dashboard",
    "metadata": {
      "source": "API"
    }
  },
  {
    "id": "NTF-00096",
    "title": "Payment success",
    "description": "Mismatch detected in GRN",
    "channel": "Slack",
    "recipient": "user11@example.com",
    "priority": "Medium",
    "status": "Failed",
    "module": "Audit",
    "entityId": "ENT-33396",
    "createdAt": "2026-05-12T12:00:00Z",
    "updatedAt": "2026-05-11T12:00:00Z",
    "scheduledAt": "2026-05-14T12:00:00Z",
    "deliveredAt": "2026-05-11T12:00:00Z",
    "deliveryAttempts": 1,
    "template": "payment-summary",
    "actionUrl": "/dashboard",
    "metadata": {
      "source": "System"
    }
  },
  {
    "id": "NTF-00097",
    "title": "Payment success",
    "description": "Retry queued for bank gateway",
    "channel": "SMS",
    "recipient": "user4@example.com",
    "priority": "Critical",
    "status": "Sent",
    "module": "Audit",
    "entityId": "ENT-71867",
    "createdAt": "2026-05-07T12:00:00Z",
    "updatedAt": "2026-05-11T12:00:00Z",
    "scheduledAt": "2026-05-10T12:00:00Z",
    "deliveredAt": "",
    "deliveryAttempts": 1,
    "template": "compliance-reminder",
    "actionUrl": "/dashboard",
    "metadata": {
      "source": "API"
    }
  },
  {
    "id": "NTF-00098",
    "title": "Vendor onboarding approved",
    "description": "Retry queued for bank gateway",
    "channel": "In-app",
    "recipient": "user19@example.com",
    "priority": "Medium",
    "status": "Read",
    "module": "Vendor",
    "entityId": "ENT-77997",
    "createdAt": "2026-05-13T12:00:00Z",
    "updatedAt": "2026-05-11T12:00:00Z",
    "scheduledAt": "2026-05-15T12:00:00Z",
    "deliveredAt": "2026-05-13T12:00:00Z",
    "deliveryAttempts": 3,
    "template": "compliance-reminder",
    "actionUrl": "/dashboard",
    "metadata": {
      "source": "User"
    }
  },
  {
    "id": "NTF-00099",
    "title": "Vendor onboarding approved",
    "description": "Payment settled successfully",
    "channel": "SMS",
    "recipient": "user8@example.com",
    "priority": "High",
    "status": "Sent",
    "module": "Invoice",
    "entityId": "ENT-93135",
    "createdAt": "2026-05-13T12:00:00Z",
    "updatedAt": "2026-05-13T12:00:00Z",
    "scheduledAt": "2026-05-09T12:00:00Z",
    "deliveredAt": "2026-05-12T12:00:00Z",
    "deliveryAttempts": 3,
    "template": "compliance-reminder",
    "actionUrl": "/dashboard",
    "metadata": {
      "source": "API"
    }
  },
  {
    "id": "NTF-00100",
    "title": "Compliance document pending",
    "description": "Retry queued for bank gateway",
    "channel": "In-app",
    "recipient": "user11@example.com",
    "priority": "Low",
    "status": "Unread",
    "module": "Vendor",
    "entityId": "ENT-24876",
    "createdAt": "2026-05-09T12:00:00Z",
    "updatedAt": "2026-05-11T12:00:00Z",
    "scheduledAt": "2026-05-11T12:00:00Z",
    "deliveredAt": "",
    "deliveryAttempts": 2,
    "template": "workflow-alert",
    "actionUrl": "/dashboard",
    "metadata": {
      "source": "API"
    }
  }
]